jrpyvisualisation/__init__.py
jrpyvisualisation/__version__.py
jrpyvisualisation/datasets/__init__.py
jrpyvisualisation/datasets/data/aphids.zip
jrpyvisualisation/datasets/data/beauty.zip
jrpyvisualisation/datasets/data/bond.zip
jrpyvisualisation/datasets/data/gapminder.zip
jrpyvisualisation/datasets/data/movies.zip
jrpyvisualisation/datasets/data/volcano.zip
jrpyvisualisation/datasets/data/volcano_db.zip
jrpyvisualisation/vignettes/practical-1.html
jrpyvisualisation/vignettes.py
jrpyvisualisation-0.1.97.dist-info/WHEEL
jrpyvisualisation-0.1.97.dist-info/METADATA
jrpyvisualisation-0.1.97.dist-info/RECORD
