Metadata-Version: 2.1
Name: jrpyvisualisation
Version: 0.1.97
Summary: Jumping Rivers: Introduction to Visualisation in Python
Author: Jamie
Author-email: jamie@jumpingrivers.com
Requires-Python: >=3.8
Classifier: Programming Language :: Python :: 3
Classifier: Programming Language :: Python :: 3.10
Classifier: Programming Language :: Python :: 3.8
Classifier: Programming Language :: Python :: 3.9
Requires-Dist: kaleido (==0.2.1)
Requires-Dist: numpy (>=1.23.2,<2.0.0)
Requires-Dist: pandas (>=1.4.3,<2.0.0)
Requires-Dist: plotly (>=4.1)
